vspyx/__init__.py
vspyx-0.0.1.dist-info/METADATA
vspyx-0.0.1.dist-info/WHEEL
vspyx-0.0.1.dist-info/top_level.txt
vspyx-0.0.1.dist-info/RECORD
