Metadata-Version: 2.1
Name: vspyx
Version: 0.0.1
Summary: Vehicle Spy X
Home-page: https://intrepidcs.com
License: UNKNOWN
Platform: UNKNOWN
Classifier: Programming Language :: Python :: 3
Classifier: License :: Other/Proprietary License
Classifier: Operating System :: OS Independent
Requires-Python: >=3.5
